setup.py
gutenberg/__init__.py
gutenberg/core.py
gutenberg/matcher.py
gutenberg/suite.py
gutenberg/util.py
gutenberg_framework.egg-info/PKG-INFO
gutenberg_framework.egg-info/SOURCES.txt
gutenberg_framework.egg-info/dependency_links.txt
gutenberg_framework.egg-info/not-zip-safe
gutenberg_framework.egg-info/requires.txt
gutenberg_framework.egg-info/top_level.txt