Metadata-Version: 1.0
Name: gutenberg-framework
Version: 0.0.3
Summary: Simple end-to-end REST API testing framework
Home-page: http://github.com/KEOTL/gutenberg
Author: Kento Lauzon
Author-email: UNKNOWN
License: GNU GPLv3
Platform: UNKNOWN
